theta/__init__.py
theta/__main__.py
theta/__version__.py
theta/audio/__init__.py
theta/cv/__init__.py
theta/cv/data/__init__.py
theta/cv/data/coco_data.py
theta/cv/templates/__init__.py
theta/cv/templates/det/__init__.py
theta/cv/templates/det/mmdet_transforms.py
theta/cv/templates/det/prepare_coco_data.py
theta/cv/templates/det/test.py
theta/cv/templates/det/train.py
theta/cv/templates/det/configs/__init__.py
theta/cv/templates/det/configs/cascade_rcnn_fpn_coco.py
theta/cv/templates/det/configs/det_cascade_rcnn_fpn_coco.py
theta/cv/templates/det/configs/rich_detect_car_params.py
theta/losses/__init__.py
theta/losses/circleloss.py
theta/losses/dice_loss.py
theta/losses/focalloss.py
theta/losses/label_smoothing.py
theta/modules/__init__.py
theta/modules/modules.py
theta/nlp/__init__.py
theta/nlp/arguments.py
theta/nlp/bert4torch/__init__.py
theta/nlp/bert4torch/activations.py
theta/nlp/bert4torch/layers.py
theta/nlp/bert4torch/losses.py
theta/nlp/bert4torch/models.py
theta/nlp/bert4torch/optimizers.py
theta/nlp/bert4torch/tokenizers.py
theta/nlp/bert4torch/utils.py
theta/nlp/eda/__init__.py
theta/nlp/eda/__main__.py
theta/nlp/entity_extraction/__init__.py
theta/nlp/entity_extraction/dataset.py
theta/nlp/entity_extraction/modeling.py
theta/nlp/entity_extraction/runner.py
theta/nlp/entity_extraction/tagging.py
theta/nlp/entity_extraction/utils.py
theta/nlp/entity_extraction/global_pointer/__init__.py
theta/nlp/entity_extraction/global_pointer/dataset.py
theta/nlp/entity_extraction/global_pointer/modeling.py
theta/nlp/entity_extraction/global_pointer/runner.py
theta/nlp/entity_extraction/global_pointer/utils.py
theta/nlp/pretrain_mlm/__init__.py
theta/nlp/pretrain_mlm/__main__.py
theta/nlp/pretrain_mlm/mlm_dataset.py
theta/nlp/relation_extraction/__init__.py
theta/nlp/relation_extraction/dataset.py
theta/nlp/relation_extraction/modeling.py
theta/nlp/relation_extraction/runner.py
theta/nlp/relation_extraction/tagging.py
theta/nlp/relation_extraction/utils.py
theta-0.51.0.dist-info/LICENSE
theta-0.51.0.dist-info/METADATA
theta-0.51.0.dist-info/WHEEL
theta-0.51.0.dist-info/entry_points.txt
theta-0.51.0.dist-info/top_level.txt
theta-0.51.0.dist-info/RECORD
