Metadata-Version: 2.1
Name: theta
Version: 0.51.0
Summary: Deep learning toolbox for end-to-end text information extraction tasks.
Home-page: https://github.com/idleuncle/theta
Author: Jiangwen Su
Author-email: 531045572@qq.com
License: MIT
Platform: UNKNOWN
Classifier: Intended Audience :: Developers
Classifier: License :: OSI Approved :: MIT License
Classifier: Operating System :: OS Independent
Classifier: Programming Language :: Python :: 3
Classifier: Programming Language :: Python :: 3.6
Classifier: Programming Language :: Python :: 3.7
Classifier: Programming Language :: Python :: 3.8
Classifier: Programming Language :: Python :: 3.9
Classifier: Topic :: Scientific/Engineering :: Artificial Intelligence
Requires-Python: >=3.7.0
Requires-Dist: numpy
Requires-Dist: tqdm (>=4.27)
Requires-Dist: torch (>=1.7.0)
Requires-Dist: dataclasses ; python_version < "3.7"
